README.md
setup.py
aio_telegraph/__init__.py
aio_telegraph/api.py
aio_telegraph/base.py
aio_telegraph/config.py
aio_telegraph/examples.py
aio_telegraph.egg-info/PKG-INFO
aio_telegraph.egg-info/SOURCES.txt
aio_telegraph.egg-info/dependency_links.txt
aio_telegraph.egg-info/top_level.txt