Metadata-Version: 2.1
Name: aio-telegraph
Version: 1.0.0
Summary: A tiny aio library for telegra.ph API
Home-page: https://github.com/bluzir/aio-telegraph
Author: Vladislav Kooklev
Author-email: kouklevv@gmail.com
License: UNKNOWN
Platform: UNKNOWN
Classifier: Programming Language :: Python :: 3
Classifier: License :: OSI Approved :: MIT License
Classifier: Operating System :: OS Independent
